source_inspector/__init__.py
source_inspector/strings_xgettext.py
source_inspector/symbols_ctags.py
source_inspector/symbols_pygments.py
source_inspector/symbols_tree_sitter.py
source_inspector-0.7.1.dist-info/licenses/AUTHORS.rst
source_inspector-0.7.1.dist-info/licenses/CHANGELOG.rst
source_inspector-0.7.1.dist-info/licenses/CODE_OF_CONDUCT.rst
source_inspector-0.7.1.dist-info/licenses/NOTICE
source_inspector-0.7.1.dist-info/licenses/apache-2.0.LICENSE
source_inspector-0.7.1.dist-info/METADATA
source_inspector-0.7.1.dist-info/WHEEL
source_inspector-0.7.1.dist-info/entry_points.txt
source_inspector-0.7.1.dist-info/top_level.txt
source_inspector-0.7.1.dist-info/RECORD
