Metadata-Version: 2.4
Name: source-inspector
Version: 0.7.1
Summary: source-inspector
Home-page: https://github.com/aboutcode-org/source-inspector
Author: nexB. Inc. and others
Author-email: info@aboutcode.org
License: Apache-2.0
Keywords: utilities
Classifier: Development Status :: 5 - Production/Stable
Classifier: Intended Audience :: Developers
Classifier: Programming Language :: Python :: 3
Classifier: Programming Language :: Python :: 3 :: Only
Classifier: Topic :: Software Development
Classifier: Topic :: Utilities
Requires-Python: >=3.10
License-File: apache-2.0.LICENSE
License-File: NOTICE
License-File: AUTHORS.rst
License-File: CHANGELOG.rst
License-File: CODE_OF_CONDUCT.rst
Requires-Dist: scancode-toolkit
Requires-Dist: plugincode
Requires-Dist: commoncode
Requires-Dist: typecode
Requires-Dist: tree-sitter==0.23.2
Requires-Dist: tree-sitter-bash==0.21.0
Requires-Dist: tree-sitter-c==0.21.1
Requires-Dist: tree-sitter-cpp==0.22.0
Requires-Dist: tree-sitter-c-sharp==0.23.1
Requires-Dist: tree-sitter-go==0.21.0
Requires-Dist: tree-sitter-java==0.21.0
Requires-Dist: tree-sitter-javascript==0.21.2
Requires-Dist: tree-sitter-objc==3.0.2
Requires-Dist: tree-sitter-python==0.21.0
Requires-Dist: tree-sitter-rust==0.21.2
Requires-Dist: tree-sitter-swift==0.0.1
Requires-Dist: pygments
Provides-Extra: dev
Requires-Dist: pytest>=7.0.1; extra == "dev"
Requires-Dist: pytest-xdist>=2; extra == "dev"
Requires-Dist: aboutcode-toolkit>=7.0.2; extra == "dev"
Requires-Dist: twine; extra == "dev"
Requires-Dist: ruff; extra == "dev"
Requires-Dist: Sphinx>=5.0.2; extra == "dev"
Requires-Dist: sphinx-rtd-theme>=1.0.0; extra == "dev"
Requires-Dist: sphinx-reredirects>=0.1.2; extra == "dev"
Requires-Dist: doc8>=0.11.2; extra == "dev"
Requires-Dist: sphinx-autobuild; extra == "dev"
Requires-Dist: sphinx-rtd-dark-mode>=1.3.0; extra == "dev"
Requires-Dist: sphinx-copybutton; extra == "dev"
Dynamic: license-file
